gdpr_api_tester/__init__.py
gdpr_api_tester/__main__.py
gdpr_api_tester/config.py
gdpr_api_tester/main.py
gdpr_api_tester/routes.py
gdpr_api_tester/rsa_key.py
gdpr_api_tester-0.1.0.dist-info/LICENSE
gdpr_api_tester-0.1.0.dist-info/METADATA
gdpr_api_tester-0.1.0.dist-info/WHEEL
gdpr_api_tester-0.1.0.dist-info/entry_points.txt
gdpr_api_tester-0.1.0.dist-info/top_level.txt
gdpr_api_tester-0.1.0.dist-info/RECORD
