Metadata-Version: 2.1
Name: gdpr-api-tester
Version: 0.1.0
Summary: Helsinki Profile GDPR API Tester
Author-email: Mikko Keskinen <mikko.keskinen@hel.fi>
License: MIT License
Project-URL: Homepage, https://github.com/City-of-Helsinki/profile-gdpr-api-tester
Project-URL: Bug Tracker, https://github.com/City-of-Helsinki/profile-gdpr-api-tester/issues
Classifier: Intended Audience :: Developers
Classifier: Environment :: Console
Classifier: License :: OSI Approved :: MIT License
Classifier: Operating System :: OS Independent
Classifier: Programming Language :: Python :: 3
Classifier: Topic :: Software Development :: Quality Assurance
Requires-Python: >=3.10
License-File: LICENSE
Requires-Dist: aioconsole ==0.5.1
Requires-Dist: aiohttp ==3.8.3
Requires-Dist: aiosignal ==1.3.1
Requires-Dist: async-timeout ==4.0.2
Requires-Dist: attrs ==22.2.0
Requires-Dist: build ==0.9.0
Requires-Dist: charset-normalizer ==2.1.1
Requires-Dist: click ==8.1.3
Requires-Dist: colorama ==0.4.6
Requires-Dist: ecdsa ==0.18.0
Requires-Dist: frozenlist ==1.3.3
Requires-Dist: idna ==3.4
Requires-Dist: multidict ==6.0.4
Requires-Dist: packaging ==22.0
Requires-Dist: pep517 ==0.13.0
Requires-Dist: pip-tools ==7.3.0
Requires-Dist: pyasn1 ==0.4.8
Requires-Dist: python-dotenv ==0.21.0
Requires-Dist: python-jose ==3.3.0
Requires-Dist: rsa ==4.9
Requires-Dist: six ==1.16.0
Requires-Dist: tomli ==2.0.1
Requires-Dist: wheel ==0.38.4
Requires-Dist: yarl ==1.8.2
